falcon_logging/__init__.py
falcon_logging/logging.py
falcon_logging-0.3.9.dist-info/LICENCE
falcon_logging-0.3.9.dist-info/METADATA
falcon_logging-0.3.9.dist-info/WHEEL
falcon_logging-0.3.9.dist-info/top_level.txt
falcon_logging-0.3.9.dist-info/RECORD
