Metadata-Version: 2.1
Name: falcon-logging
Version: 0.3.9
Summary: Logging Wrapper for Falcon Web Framework with Cloud Logging
Home-page: UNKNOWN
Author: SantoLabs
Author-email: santolabs@santodigital.com.br
License: UNKNOWN
Platform: UNKNOWN
Classifier: Programming Language :: Python :: 3
Classifier: License :: OSI Approved :: MIT License
Classifier: Operating System :: OS Independent
Requires-Python: >=3.6
License-File: LICENCE
